{
  "attorneys": [
    {
      "address": null,
      "attorney_id": "name:4576f1d792d0fe62",
      "bar_number": null,
      "case_number": "203041347SEA",
      "contact_block": null,
      "name": "Petition - filed on 09/02/2020 Disposed as DSM - Dismissal Without Trial on 11/17/2020",
      "parties_represented": [
        {
          "name": "Petition - filed on 09/02/2020 Disposed as DSM - Dismissal Without Trial on 11/17/2020",
          "party_seq": 1
        }
      ],
      "raw": [
        {
          "caseNumber": "20-3-04134-7 SEA",
          "caseTypeKey": "family",
          "name": "Petition - filed on 09/02/2020 Disposed as DSM - Dismissal Without Trial on 11/17/2020",
          "portalCaseId": "2812969",
          "rawCells": [
            "- filed on 08/25/2020 Disposed as TRJG - Transfer Of Judgment on 08/25/2020",
            "Petition - filed on 09/02/2020 Disposed as DSM - Dismissal Without Trial on 11/17/2020",
            "Petition - filed on 09/02/2020 Disposed as DSM - Dismissal Without Trial on 11/17/2020"
          ],
          "rawHeaders": [
            "Type",
            "Name",
            "Represented By"
          ],
          "rawLine": "- filed on 08/25/2020 Disposed as TRJG - Transfer Of Judgment on 08/25/2020\tPetition - filed on 09/02/2020 Disposed as DSM - Dismissal Without Trial on 11/17/2020\tPetition - filed on 09/02/2020 Disposed as DSM - Dismissal Without Trial on 11/17/2020",
          "rawTabId": "2812969:participants",
          "recordId": "2812969:participants:row:1",
          "representedBy": "Petition - filed on 09/02/2020 Disposed as DSM - Dismissal Without Trial on 11/17/2020",
          "rowIndex": 1,
          "section": "Out of State Support Registration /Foreign Judgment (3) - Completed/Re-Completed",
          "tabKey": "participants",
          "type": "- filed on 08/25/2020 Disposed as TRJG - Transfer Of Judgment on 08/25/2020"
        }
      ],
      "source": "kcsc.participants"
    }
  ],
  "calendar": [
    {
      "calendar_seq": 1,
      "case_number": "203041347SEA",
      "court_date": "2020-11-13",
      "department": null,
      "hearing_time": "08:45",
      "hearing_type": "Motions for Trial By Affidavit",
      "judge": "DISMISSAL",
      "location": null,
      "matters": "DISMISSAL",
      "raw": {
        "additionalInfo": "DISMISSAL",
        "caseNumber": "20-3-04134-7 SEA",
        "caseTypeKey": "family",
        "dateTime": "11/13/2020 08:45 AM",
        "portalCaseId": "2812969",
        "rawCells": [
          "11/13/2020 08:45 AM",
          "Motions for Trial By Affidavit",
          "DISMISSAL"
        ],
        "rawHeaders": [
          "Date/Time",
          "Type",
          "Additional Info",
          "Official",
          "Location"
        ],
        "rawLine": "\t  11/13/2020 08:45 AM\tMotions for Trial By Affidavit\tDISMISSAL\t\t",
        "rawTabId": "2812969:events_docket",
        "recordId": "2812969:events_docket:row:1",
        "rowIndex": 1,
        "section": "Hearings",
        "tabKey": "events_docket",
        "type": "Motions for Trial By Affidavit"
      },
      "source": "kcsc.events"
    },
    {
      "calendar_seq": 2,
      "case_number": "203041347SEA",
      "court_date": "2020-10-30",
      "department": null,
      "hearing_time": "08:45",
      "hearing_type": "Motions for Trial By Affidavit",
      "judge": "DISMISSAL",
      "location": null,
      "matters": "DISMISSAL",
      "raw": {
        "additionalInfo": "DISMISSAL",
        "caseNumber": "20-3-04134-7 SEA",
        "caseTypeKey": "family",
        "dateTime": "10/30/2020 08:45 AM",
        "portalCaseId": "2812969",
        "rawCells": [
          "10/30/2020 08:45 AM",
          "Motions for Trial By Affidavit",
          "DISMISSAL"
        ],
        "rawHeaders": [
          "Date/Time",
          "Type",
          "Additional Info",
          "Official",
          "Location"
        ],
        "rawLine": "\t  10/30/2020 08:45 AM\tMotions for Trial By Affidavit\tDISMISSAL\t\t",
        "rawTabId": "2812969:events_docket",
        "recordId": "2812969:events_docket:row:2",
        "rowIndex": 2,
        "section": "Hearings",
        "tabKey": "events_docket",
        "type": "Motions for Trial By Affidavit"
      },
      "source": "kcsc.events"
    }
  ],
  "captured_at": "2026-07-15T05:10:42.768Z",
  "case_number": "203041347SEA",
  "case_title": "SANTAMARIA AKA VS BENNETT",
  "case_type": "family",
  "cause_of_action": "Out of State Support Registration /Foreign Judgment (3)",
  "court": "King County Superior Court",
  "court_id": "kcsc",
  "display_case_number": "20-3-04134-7 SEA",
  "docket_entries": [
    {
      "case_number": "203041347SEA",
      "date_filed": "2020-09-02",
      "description": "Petition - MDS - Modification/Support Only filed on 09/02/2020",
      "doc_id": null,
      "entry_seq": 1,
      "fee": null,
      "has_document": false,
      "raw": {
        "caseNumber": "20-3-04134-7 SEA",
        "caseTypeKey": "family",
        "portalCaseId": "2812969",
        "rawCells": [
          "Petition - MDS - Modification/Support Only filed on 09/02/2020"
        ],
        "rawHeaders": [
          "SubCase",
          "Due Date"
        ],
        "rawLine": "\t  Petition - MDS - Modification/Support Only filed on 09/02/2020",
        "rawTabId": "2812969:events_docket",
        "recordId": "2812969:events_docket:row:4",
        "rowIndex": 4,
        "section": "Case Schedule - SubCase",
        "subcase": "Petition - MDS - Modification/Support Only filed on 09/02/2020",
        "tabKey": "events_docket"
      },
      "source": "kcsc.events",
      "url": null
    },
    {
      "case_number": "203041347SEA",
      "date_filed": "2020-09-24",
      "description": "Declaration of Financial Information",
      "doc_id": null,
      "entry_seq": 2,
      "fee": null,
      "has_document": false,
      "raw": {
        "caseNumber": "20-3-04134-7 SEA",
        "caseTypeKey": "family",
        "dueDate": "09/24/2020",
        "portalCaseId": "2812969",
        "rawCells": [
          "Declaration of Financial Information",
          "09/24/2020"
        ],
        "rawHeaders": [
          "SubCase",
          "Due Date"
        ],
        "rawLine": "\t    Declaration of Financial Information\t09/24/2020",
        "rawTabId": "2812969:events_docket",
        "recordId": "2812969:events_docket:row:5",
        "rowIndex": 5,
        "section": "Case Schedule - SubCase",
        "subcase": "Declaration of Financial Information",
        "tabKey": "events_docket"
      },
      "source": "kcsc.events",
      "url": null
    },
    {
      "case_number": "203041347SEA",
      "date_filed": "2020-12-04",
      "description": "Trial Memoranda",
      "doc_id": null,
      "entry_seq": 3,
      "fee": null,
      "has_document": false,
      "raw": {
        "caseNumber": "20-3-04134-7 SEA",
        "caseTypeKey": "family",
        "dueDate": "12/04/2020",
        "portalCaseId": "2812969",
        "rawCells": [
          "Trial Memoranda",
          "12/04/2020"
        ],
        "rawHeaders": [
          "SubCase",
          "Due Date"
        ],
        "rawLine": "\t    Trial Memoranda\t12/04/2020",
        "rawTabId": "2812969:events_docket",
        "recordId": "2812969:events_docket:row:6",
        "rowIndex": 6,
        "section": "Case Schedule - SubCase",
        "subcase": "Trial Memoranda",
        "tabKey": "events_docket"
      },
      "source": "kcsc.events",
      "url": null
    },
    {
      "case_number": "203041347SEA",
      "date_filed": "2020-12-18",
      "description": "Trial Date",
      "doc_id": null,
      "entry_seq": 4,
      "fee": null,
      "has_document": false,
      "raw": {
        "caseNumber": "20-3-04134-7 SEA",
        "caseTypeKey": "family",
        "dueDate": "12/18/2020",
        "portalCaseId": "2812969",
        "rawCells": [
          "Trial Date",
          "12/18/2020"
        ],
        "rawHeaders": [
          "SubCase",
          "Due Date"
        ],
        "rawLine": "\t    Trial Date\t12/18/2020",
        "rawTabId": "2812969:events_docket",
        "recordId": "2812969:events_docket:row:7",
        "rowIndex": 7,
        "section": "Case Schedule - SubCase",
        "subcase": "Trial Date",
        "tabKey": "events_docket"
      },
      "source": "kcsc.events",
      "url": null
    },
    {
      "case_number": "203041347SEA",
      "date_filed": "2020-11-20",
      "description": "Discovery Cutoff",
      "doc_id": null,
      "entry_seq": 5,
      "fee": null,
      "has_document": false,
      "raw": {
        "caseNumber": "20-3-04134-7 SEA",
        "caseTypeKey": "family",
        "dueDate": "11/20/2020",
        "portalCaseId": "2812969",
        "rawCells": [
          "Discovery Cutoff",
          "11/20/2020"
        ],
        "rawHeaders": [
          "SubCase",
          "Due Date"
        ],
        "rawLine": "\t    Discovery Cutoff\t11/20/2020",
        "rawTabId": "2812969:events_docket",
        "recordId": "2812969:events_docket:row:8",
        "rowIndex": 8,
        "section": "Case Schedule - SubCase",
        "subcase": "Discovery Cutoff",
        "tabKey": "events_docket"
      },
      "source": "kcsc.events",
      "url": null
    },
    {
      "case_number": "203041347SEA",
      "date_filed": "2020-10-08",
      "description": "DEADLINE to File a Motion Requesting Testimony",
      "doc_id": null,
      "entry_seq": 6,
      "fee": null,
      "has_document": false,
      "raw": {
        "caseNumber": "20-3-04134-7 SEA",
        "caseTypeKey": "family",
        "dueDate": "10/08/2020",
        "portalCaseId": "2812969",
        "rawCells": [
          "DEADLINE to File a Motion Requesting Testimony",
          "10/08/2020"
        ],
        "rawHeaders": [
          "SubCase",
          "Due Date"
        ],
        "rawLine": "\t    DEADLINE to File a Motion Requesting Testimony\t10/08/2020",
        "rawTabId": "2812969:events_docket",
        "recordId": "2812969:events_docket:row:9",
        "rowIndex": 9,
        "section": "Case Schedule - SubCase",
        "subcase": "DEADLINE to File a Motion Requesting Testimony",
        "tabKey": "events_docket"
      },
      "source": "kcsc.events",
      "url": null
    },
    {
      "case_number": "203041347SEA",
      "date_filed": "2020-09-24",
      "description": "Answer or narrative affidavit",
      "doc_id": null,
      "entry_seq": 7,
      "fee": null,
      "has_document": false,
      "raw": {
        "caseNumber": "20-3-04134-7 SEA",
        "caseTypeKey": "family",
        "dueDate": "09/24/2020",
        "portalCaseId": "2812969",
        "rawCells": [
          "Answer or narrative affidavit",
          "09/24/2020"
        ],
        "rawHeaders": [
          "SubCase",
          "Due Date"
        ],
        "rawLine": "\t    Answer or narrative affidavit\t09/24/2020",
        "rawTabId": "2812969:events_docket",
        "recordId": "2812969:events_docket:row:10",
        "rowIndex": 10,
        "section": "Case Schedule - SubCase",
        "subcase": "Answer or narrative affidavit",
        "tabKey": "events_docket"
      },
      "source": "kcsc.events",
      "url": null
    },
    {
      "case_number": "203041347SEA",
      "date_filed": "2020-12-11",
      "description": "Responsive/Reply Memoranda",
      "doc_id": null,
      "entry_seq": 8,
      "fee": null,
      "has_document": false,
      "raw": {
        "caseNumber": "20-3-04134-7 SEA",
        "caseTypeKey": "family",
        "dueDate": "12/11/2020",
        "portalCaseId": "2812969",
        "rawCells": [
          "Responsive/Reply Memoranda",
          "12/11/2020"
        ],
        "rawHeaders": [
          "SubCase",
          "Due Date"
        ],
        "rawLine": "\t    Responsive/Reply Memoranda\t12/11/2020",
        "rawTabId": "2812969:events_docket",
        "recordId": "2812969:events_docket:row:11",
        "rowIndex": 11,
        "section": "Case Schedule - SubCase",
        "subcase": "Responsive/Reply Memoranda",
        "tabKey": "events_docket"
      },
      "source": "kcsc.events",
      "url": null
    },
    {
      "case_number": "203041347SEA",
      "date_filed": "2020-12-04",
      "description": "Motion to Change Trial Date",
      "doc_id": null,
      "entry_seq": 9,
      "fee": null,
      "has_document": false,
      "raw": {
        "caseNumber": "20-3-04134-7 SEA",
        "caseTypeKey": "family",
        "dueDate": "12/04/2020",
        "portalCaseId": "2812969",
        "rawCells": [
          "Motion to Change Trial Date",
          "12/04/2020"
        ],
        "rawHeaders": [
          "SubCase",
          "Due Date"
        ],
        "rawLine": "\t    Motion to Change Trial Date\t12/04/2020",
        "rawTabId": "2812969:events_docket",
        "recordId": "2812969:events_docket:row:12",
        "rowIndex": 12,
        "section": "Case Schedule - SubCase",
        "subcase": "Motion to Change Trial Date",
        "tabKey": "events_docket"
      },
      "source": "kcsc.events",
      "url": null
    },
    {
      "case_number": "203041347SEA",
      "date_filed": "2020-12-11",
      "description": "Confirmation of Trial",
      "doc_id": null,
      "entry_seq": 10,
      "fee": null,
      "has_document": false,
      "raw": {
        "caseNumber": "20-3-04134-7 SEA",
        "caseTypeKey": "family",
        "dueDate": "12/11/2020",
        "portalCaseId": "2812969",
        "rawCells": [
          "Confirmation of Trial",
          "12/11/2020"
        ],
        "rawHeaders": [
          "SubCase",
          "Due Date"
        ],
        "rawLine": "\t    Confirmation of Trial\t12/11/2020",
        "rawTabId": "2812969:events_docket",
        "recordId": "2812969:events_docket:row:13",
        "rowIndex": 13,
        "section": "Case Schedule - SubCase",
        "subcase": "Confirmation of Trial",
        "tabKey": "events_docket"
      },
      "source": "kcsc.events",
      "url": null
    },
    {
      "case_number": "203041347SEA",
      "date_filed": "2020-09-03",
      "description": "Declaration of Financial Information",
      "doc_id": null,
      "entry_seq": 11,
      "fee": null,
      "has_document": false,
      "raw": {
        "caseNumber": "20-3-04134-7 SEA",
        "caseTypeKey": "family",
        "dueDate": "09/03/2020",
        "portalCaseId": "2812969",
        "rawCells": [
          "Declaration of Financial Information",
          "09/03/2020"
        ],
        "rawHeaders": [
          "SubCase",
          "Due Date"
        ],
        "rawLine": "\t    Declaration of Financial Information\t09/03/2020",
        "rawTabId": "2812969:events_docket",
        "recordId": "2812969:events_docket:row:14",
        "rowIndex": 14,
        "section": "Case Schedule - SubCase",
        "subcase": "Declaration of Financial Information",
        "tabKey": "events_docket"
      },
      "source": "kcsc.events",
      "url": null
    },
    {
      "case_number": "203041347SEA",
      "date_filed": "2020-12-11",
      "description": "Working Papers",
      "doc_id": null,
      "entry_seq": 12,
      "fee": null,
      "has_document": false,
      "raw": {
        "caseNumber": "20-3-04134-7 SEA",
        "caseTypeKey": "family",
        "dueDate": "12/11/2020",
        "portalCaseId": "2812969",
        "rawCells": [
          "Working Papers",
          "12/11/2020"
        ],
        "rawHeaders": [
          "SubCase",
          "Due Date"
        ],
        "rawLine": "\t    Working Papers\t12/11/2020",
        "rawTabId": "2812969:events_docket",
        "recordId": "2812969:events_docket:row:15",
        "rowIndex": 15,
        "section": "Case Schedule - SubCase",
        "subcase": "Working Papers",
        "tabKey": "events_docket"
      },
      "source": "kcsc.events",
      "url": null
    },
    {
      "case_number": "203041347SEA",
      "date_filed": null,
      "description": "Time Standards",
      "doc_id": null,
      "entry_seq": 13,
      "fee": null,
      "has_document": false,
      "raw": {
        "caseNumber": "20-3-04134-7 SEA",
        "caseTypeKey": "family",
        "portalCaseId": "2812969",
        "rawCells": [
          "Time Standards"
        ],
        "rawHeaders": [
          "SubCase",
          "Due Date"
        ],
        "rawLine": "Time Standards ",
        "rawTabId": "2812969:events_docket",
        "recordId": "2812969:events_docket:row:16",
        "rowIndex": 16,
        "section": "Case Schedule - SubCase",
        "subcase": "Time Standards",
        "tabKey": "events_docket"
      },
      "source": "kcsc.events",
      "url": null
    }
  ],
  "document_unavailable_reason": "document byte capture not implemented for KCSC yet",
  "documents": [],
  "documents_deferred": true,
  "filed_date": "2020-08-25",
  "filing_date": "2020-08-25",
  "jurisdiction": "King County, WA",
  "kcsc": {
    "case_type_key": "family",
    "case_type_text": "3 - Domestic",
    "charge_rows": [],
    "date_text": "08/25/2020",
    "detail_error": {},
    "detail_status": "captured",
    "detail_unavailable_reason": null,
    "document_byte_capture": "not_attempted",
    "document_rows_deferred": [
      {
        "additionalInformation": "34",
        "caseNumber": "20-3-04134-7 SEA",
        "caseTypeKey": "family",
        "dateFiled": "08/25/2020",
        "documentName": "RQSREG - Request for Support Order Registration",
        "portalCaseId": "2812969",
        "rawCells": [
          "1",
          "08/25/2020",
          "RQSREG - Request for Support Order Registration",
          "34"
        ],
        "rawHeaders": [
          "Sub Number",
          "Date Filed",
          "Document Name",
          "Additional Information",
          "Filed By",
          "Page #",
          "Seal"
        ],
        "rawLine": "\t  1\t08/25/2020\tRQSREG - Request for Support Order Registration\t\t\t34\t",
        "rawTabId": "2812969:documents",
        "recordId": "2812969:documents:row:1",
        "rowIndex": 1,
        "section": "Documents List",
        "subNumber": "1",
        "tabKey": "documents"
      },
      {
        "additionalInformation": "OF STIPULATED CUSTODY AND VISITATION ORDER",
        "caseNumber": "20-3-04134-7 SEA",
        "caseTypeKey": "family",
        "dateFiled": "08/25/2020",
        "documentName": "CP - Copy",
        "filedBy": "14",
        "portalCaseId": "2812969",
        "rawCells": [
          "2",
          "08/25/2020",
          "CP - Copy",
          "OF STIPULATED CUSTODY AND VISITATION ORDER",
          "14"
        ],
        "rawHeaders": [
          "Sub Number",
          "Date Filed",
          "Document Name",
          "Additional Information",
          "Filed By",
          "Page #",
          "Seal"
        ],
        "rawLine": "\t  2\t08/25/2020\tCP - Copy\tOF STIPULATED CUSTODY AND VISITATION ORDER\t\t14\t",
        "rawTabId": "2812969:documents",
        "recordId": "2812969:documents:row:2",
        "rowIndex": 2,
        "section": "Documents List",
        "subNumber": "2",
        "tabKey": "documents"
      },
      {
        "additionalInformation": "1",
        "caseNumber": "20-3-04134-7 SEA",
        "caseTypeKey": "family",
        "dateFiled": "08/25/2020",
        "documentName": "CICS - Case Information Cover Sheet",
        "portalCaseId": "2812969",
        "rawCells": [
          "3",
          "08/25/2020",
          "CICS - Case Information Cover Sheet",
          "1"
        ],
        "rawHeaders": [
          "Sub Number",
          "Date Filed",
          "Document Name",
          "Additional Information",
          "Filed By",
          "Page #",
          "Seal"
        ],
        "rawLine": "\t  3\t08/25/2020\tCICS - Case Information Cover Sheet\t\t\t1\t",
        "rawTabId": "2812969:documents",
        "recordId": "2812969:documents:row:3",
        "rowIndex": 3,
        "section": "Documents List",
        "subNumber": "3",
        "tabKey": "documents"
      },
      {
        "additionalInformation": "2",
        "caseNumber": "20-3-04134-7 SEA",
        "caseTypeKey": "family",
        "dateFiled": "08/25/2020",
        "documentName": "CIF - Confidential Information Form",
        "portalCaseId": "2812969",
        "rawCells": [
          "4",
          "08/25/2020",
          "CIF - Confidential Information Form",
          "2"
        ],
        "rawHeaders": [
          "Sub Number",
          "Date Filed",
          "Document Name",
          "Additional Information",
          "Filed By",
          "Page #",
          "Seal"
        ],
        "rawLine": "\t  4\t08/25/2020\tCIF - Confidential Information Form\t\t\t2\t",
        "rawTabId": "2812969:documents",
        "recordId": "2812969:documents:row:4",
        "rowIndex": 4,
        "section": "Documents List",
        "subNumber": "4",
        "tabKey": "documents"
      },
      {
        "additionalInformation": "2",
        "caseNumber": "20-3-04134-7 SEA",
        "caseTypeKey": "family",
        "dateFiled": "09/02/2020",
        "documentName": "DCLRM - Declaration of Mailing",
        "portalCaseId": "2812969",
        "rawCells": [
          "5",
          "09/02/2020",
          "DCLRM - Declaration of Mailing",
          "2"
        ],
        "rawHeaders": [
          "Sub Number",
          "Date Filed",
          "Document Name",
          "Additional Information",
          "Filed By",
          "Page #",
          "Seal"
        ],
        "rawLine": "\t  5\t09/02/2020\tDCLRM - Declaration of Mailing\t\t\t2\t",
        "rawTabId": "2812969:documents",
        "recordId": "2812969:documents:row:5",
        "rowIndex": 5,
        "section": "Documents List",
        "subNumber": "5",
        "tabKey": "documents"
      },
      {
        "additionalInformation": "Petitioner - VANESSA GUYER",
        "caseNumber": "20-3-04134-7 SEA",
        "caseTypeKey": "family",
        "dateFiled": "09/02/2020",
        "documentName": "NTCUSDR - Notice of Custody Determination Registration",
        "filedBy": "37",
        "portalCaseId": "2812969",
        "rawCells": [
          "6",
          "09/02/2020",
          "NTCUSDR - Notice of Custody Determination Registration",
          "Petitioner - VANESSA GUYER",
          "37"
        ],
        "rawHeaders": [
          "Sub Number",
          "Date Filed",
          "Document Name",
          "Additional Information",
          "Filed By",
          "Page #",
          "Seal"
        ],
        "rawLine": "\t  6\t09/02/2020\tNTCUSDR - Notice of Custody Determination Registration\t\tPetitioner - VANESSA GUYER\t37\t",
        "rawTabId": "2812969:documents",
        "recordId": "2812969:documents:row:6",
        "rowIndex": 6,
        "section": "Documents List",
        "subNumber": "6",
        "tabKey": "documents"
      },
      {
        "additionalInformation": "4",
        "caseNumber": "20-3-04134-7 SEA",
        "caseTypeKey": "family",
        "dateFiled": "09/02/2020",
        "documentName": "CICS - Case Information Cover Sheet",
        "portalCaseId": "2812969",
        "rawCells": [
          "7",
          "09/02/2020",
          "CICS - Case Information Cover Sheet",
          "4"
        ],
        "rawHeaders": [
          "Sub Number",
          "Date Filed",
          "Document Name",
          "Additional Information",
          "Filed By",
          "Page #",
          "Seal"
        ],
        "rawLine": "\t  7\t09/02/2020\tCICS - Case Information Cover Sheet\t\t\t4\t",
        "rawTabId": "2812969:documents",
        "recordId": "2812969:documents:row:7",
        "rowIndex": 7,
        "section": "Documents List",
        "subNumber": "7",
        "tabKey": "documents"
      },
      {
        "additionalInformation": "Petitioner - VANESSA GUYER",
        "caseNumber": "20-3-04134-7 SEA",
        "caseTypeKey": "family",
        "dateFiled": "09/02/2020",
        "documentName": "CIFS - Confidential Information - Subsequent",
        "filedBy": "2",
        "portalCaseId": "2812969",
        "rawCells": [
          "8",
          "09/02/2020",
          "CIFS - Confidential Information - Subsequent",
          "Petitioner - VANESSA GUYER",
          "2"
        ],
        "rawHeaders": [
          "Sub Number",
          "Date Filed",
          "Document Name",
          "Additional Information",
          "Filed By",
          "Page #",
          "Seal"
        ],
        "rawLine": "\t  8\t09/02/2020\tCIFS - Confidential Information - Subsequent\t\tPetitioner - VANESSA GUYER\t2\t",
        "rawTabId": "2812969:documents",
        "recordId": "2812969:documents:row:8",
        "rowIndex": 8,
        "section": "Documents List",
        "subNumber": "8",
        "tabKey": "documents"
      },
      {
        "additionalInformation": "Petitioner - VANESSA GUYER",
        "caseNumber": "20-3-04134-7 SEA",
        "caseTypeKey": "family",
        "dateFiled": "09/02/2020",
        "documentName": "SM - Summons",
        "filedBy": "3",
        "portalCaseId": "2812969",
        "rawCells": [
          "9",
          "09/02/2020",
          "SM - Summons",
          "Petitioner - VANESSA GUYER",
          "3"
        ],
        "rawHeaders": [
          "Sub Number",
          "Date Filed",
          "Document Name",
          "Additional Information",
          "Filed By",
          "Page #",
          "Seal"
        ],
        "rawLine": "\t  9\t09/02/2020\tSM - Summons\t\tPetitioner - VANESSA GUYER\t3\t",
        "rawTabId": "2812969:documents",
        "recordId": "2812969:documents:row:9",
        "rowIndex": 9,
        "section": "Documents List",
        "subNumber": "9",
        "tabKey": "documents"
      },
      {
        "additionalInformation": "Petitioner - VANESSA GUYER",
        "caseNumber": "20-3-04134-7 SEA",
        "caseTypeKey": "family",
        "dateFiled": "09/02/2020",
        "documentName": "FNDCLRP - Financial Declaration of Petitioner",
        "filedBy": "6",
        "portalCaseId": "2812969",
        "rawCells": [
          "11",
          "09/02/2020",
          "FNDCLRP - Financial Declaration of Petitioner",
          "Petitioner - VANESSA GUYER",
          "6"
        ],
        "rawHeaders": [
          "Sub Number",
          "Date Filed",
          "Document Name",
          "Additional Information",
          "Filed By",
          "Page #",
          "Seal"
        ],
        "rawLine": "\t  11\t09/02/2020\tFNDCLRP - Financial Declaration of Petitioner\t\tPetitioner - VANESSA GUYER\t6\t",
        "rawTabId": "2812969:documents",
        "recordId": "2812969:documents:row:10",
        "rowIndex": 10,
        "section": "Documents List",
        "subNumber": "11",
        "tabKey": "documents"
      },
      {
        "additionalInformation": "5",
        "caseNumber": "20-3-04134-7 SEA",
        "caseTypeKey": "family",
        "dateFiled": "09/02/2020",
        "documentName": "CSWP - Child Support Worksheet/Proposed",
        "portalCaseId": "2812969",
        "rawCells": [
          "12",
          "09/02/2020",
          "CSWP - Child Support Worksheet/Proposed",
          "5"
        ],
        "rawHeaders": [
          "Sub Number",
          "Date Filed",
          "Document Name",
          "Additional Information",
          "Filed By",
          "Page #",
          "Seal"
        ],
        "rawLine": "\t  12\t09/02/2020\tCSWP - Child Support Worksheet/Proposed\t\t\t5\t",
        "rawTabId": "2812969:documents",
        "recordId": "2812969:documents:row:11",
        "rowIndex": 11,
        "section": "Documents List",
        "subNumber": "12",
        "tabKey": "documents"
      },
      {
        "additionalInformation": "90",
        "caseNumber": "20-3-04134-7 SEA",
        "caseTypeKey": "family",
        "dateFiled": "09/02/2020",
        "documentName": "SEALFN - Sealed Financial Source Document(s)",
        "portalCaseId": "2812969",
        "rawCells": [
          "13",
          "09/02/2020",
          "SEALFN - Sealed Financial Source Document(s)",
          "90"
        ],
        "rawHeaders": [
          "Sub Number",
          "Date Filed",
          "Document Name",
          "Additional Information",
          "Filed By",
          "Page #",
          "Seal"
        ],
        "rawLine": "\t  13\t09/02/2020\tSEALFN - Sealed Financial Source Document(s)\t\t\t90\t",
        "rawTabId": "2812969:documents",
        "recordId": "2812969:documents:row:12",
        "rowIndex": 12,
        "section": "Documents List",
        "subNumber": "13",
        "tabKey": "documents"
      },
      {
        "additionalInformation": "Petitioner - VANESSA GUYER",
        "caseNumber": "20-3-04134-7 SEA",
        "caseTypeKey": "family",
        "dateFiled": "09/02/2020",
        "documentName": "PTMDSP - Petition for Modification of Support (Subsequent)",
        "filedBy": "24",
        "portalCaseId": "2812969",
        "rawCells": [
          "14",
          "09/02/2020",
          "PTMDSP - Petition for Modification of Support (Subsequent)",
          "Petitioner - VANESSA GUYER",
          "24"
        ],
        "rawHeaders": [
          "Sub Number",
          "Date Filed",
          "Document Name",
          "Additional Information",
          "Filed By",
          "Page #",
          "Seal"
        ],
        "rawLine": "\t  14\t09/02/2020\tPTMDSP - Petition for Modification of Support (Subsequent)\t\tPetitioner - VANESSA GUYER\t24\t",
        "rawTabId": "2812969:documents",
        "recordId": "2812969:documents:row:13",
        "rowIndex": 13,
        "section": "Documents List",
        "subNumber": "14",
        "tabKey": "documents"
      },
      {
        "additionalInformation": "Clerk",
        "caseNumber": "20-3-04134-7 SEA",
        "caseTypeKey": "family",
        "dateFiled": "09/02/2020",
        "documentName": "FAULTY - Faulty Document Notice",
        "filedBy": "1",
        "portalCaseId": "2812969",
        "rawCells": [
          "15",
          "09/02/2020",
          "FAULTY - Faulty Document Notice",
          "Clerk",
          "1"
        ],
        "rawHeaders": [
          "Sub Number",
          "Date Filed",
          "Document Name",
          "Additional Information",
          "Filed By",
          "Page #",
          "Seal"
        ],
        "rawLine": "\t  15\t09/02/2020\tFAULTY - Faulty Document Notice\t\tClerk\t1\t",
        "rawTabId": "2812969:documents",
        "recordId": "2812969:documents:row:14",
        "rowIndex": 14,
        "section": "Documents List",
        "subNumber": "15",
        "tabKey": "documents"
      },
      {
        "additionalInformation": "Clerk",
        "caseNumber": "20-3-04134-7 SEA",
        "caseTypeKey": "family",
        "dateFiled": "09/02/2020",
        "documentName": "ORSCS-DS - Order Setting Case Schedule - Domestic Support Mod",
        "filedBy": "5",
        "portalCaseId": "2812969",
        "rawCells": [
          "16",
          "09/02/2020",
          "ORSCS-DS - Order Setting Case Schedule - Domestic Support Mod",
          "Clerk",
          "5"
        ],
        "rawHeaders": [
          "Sub Number",
          "Date Filed",
          "Document Name",
          "Additional Information",
          "Filed By",
          "Page #",
          "Seal"
        ],
        "rawLine": "\t  16\t09/02/2020\tORSCS-DS - Order Setting Case Schedule - Domestic Support Mod\t\tClerk\t5\t",
        "rawTabId": "2812969:documents",
        "recordId": "2812969:documents:row:15",
        "rowIndex": 15,
        "section": "Documents List",
        "subNumber": "16",
        "tabKey": "documents"
      },
      {
        "additionalInformation": "REGARDING ORDER SETTING CASE SCHEDULE",
        "caseNumber": "20-3-04134-7 SEA",
        "caseTypeKey": "family",
        "dateFiled": "09/03/2020",
        "documentName": "NT - Notice",
        "filedBy": "6",
        "portalCaseId": "2812969",
        "rawCells": [
          "17",
          "09/03/2020",
          "NT - Notice",
          "REGARDING ORDER SETTING CASE SCHEDULE",
          "6"
        ],
        "rawHeaders": [
          "Sub Number",
          "Date Filed",
          "Document Name",
          "Additional Information",
          "Filed By",
          "Page #",
          "Seal"
        ],
        "rawLine": "\t  17\t09/03/2020\tNT - Notice\tREGARDING ORDER SETTING CASE SCHEDULE\t\t6\t",
        "rawTabId": "2812969:documents",
        "recordId": "2812969:documents:row:16",
        "rowIndex": 16,
        "section": "Documents List",
        "subNumber": "17",
        "tabKey": "documents"
      },
      {
        "additionalInformation": "1",
        "caseNumber": "20-3-04134-7 SEA",
        "caseTypeKey": "family",
        "dateFiled": "09/14/2020",
        "documentName": "AFSR - Affidavit / Declaration / Certificate Of Service",
        "portalCaseId": "2812969",
        "rawCells": [
          "19",
          "09/14/2020",
          "AFSR - Affidavit / Declaration / Certificate Of Service",
          "1"
        ],
        "rawHeaders": [
          "Sub Number",
          "Date Filed",
          "Document Name",
          "Additional Information",
          "Filed By",
          "Page #",
          "Seal"
        ],
        "rawLine": "\t  19\t09/14/2020\tAFSR - Affidavit / Declaration / Certificate Of Service\t\t\t1\t",
        "rawTabId": "2812969:documents",
        "recordId": "2812969:documents:row:17",
        "rowIndex": 17,
        "section": "Documents List",
        "subNumber": "19",
        "tabKey": "documents"
      },
      {
        "additionalInformation": "2",
        "caseNumber": "20-3-04134-7 SEA",
        "caseTypeKey": "family",
        "dateFiled": "09/15/2020",
        "documentName": "RCPCM - Receipt Certified Mail",
        "portalCaseId": "2812969",
        "rawCells": [
          "18",
          "09/15/2020",
          "RCPCM - Receipt Certified Mail",
          "2"
        ],
        "rawHeaders": [
          "Sub Number",
          "Date Filed",
          "Document Name",
          "Additional Information",
          "Filed By",
          "Page #",
          "Seal"
        ],
        "rawLine": "\t  18\t09/15/2020\tRCPCM - Receipt Certified Mail\t\t\t2\t",
        "rawTabId": "2812969:documents",
        "recordId": "2812969:documents:row:18",
        "rowIndex": 18,
        "section": "Documents List",
        "subNumber": "18",
        "tabKey": "documents"
      },
      {
        "additionalInformation": "2",
        "caseNumber": "20-3-04134-7 SEA",
        "caseTypeKey": "family",
        "dateFiled": "09/16/2020",
        "documentName": "DCLRM - Declaration of Mailing",
        "portalCaseId": "2812969",
        "rawCells": [
          "20",
          "09/16/2020",
          "DCLRM - Declaration of Mailing",
          "2"
        ],
        "rawHeaders": [
          "Sub Number",
          "Date Filed",
          "Document Name",
          "Additional Information",
          "Filed By",
          "Page #",
          "Seal"
        ],
        "rawLine": "\t  20\t09/16/2020\tDCLRM - Declaration of Mailing\t\t\t2\t",
        "rawTabId": "2812969:documents",
        "recordId": "2812969:documents:row:19",
        "rowIndex": 19,
        "section": "Documents List",
        "subNumber": "20",
        "tabKey": "documents"
      },
      {
        "additionalInformation": "Respondent - STEPHEN BENNETT",
        "caseNumber": "20-3-04134-7 SEA",
        "caseTypeKey": "family",
        "dateFiled": "09/22/2020",
        "documentName": "NTAPR - Notice of Appearance",
        "filedBy": "2",
        "portalCaseId": "2812969",
        "rawCells": [
          "21",
          "09/22/2020",
          "NTAPR - Notice of Appearance",
          "Respondent - STEPHEN BENNETT",
          "2"
        ],
        "rawHeaders": [
          "Sub Number",
          "Date Filed",
          "Document Name",
          "Additional Information",
          "Filed By",
          "Page #",
          "Seal"
        ],
        "rawLine": "\t  21\t09/22/2020\tNTAPR - Notice of Appearance\t\tRespondent - STEPHEN BENNETT\t2\t",
        "rawTabId": "2812969:documents",
        "recordId": "2812969:documents:row:20",
        "rowIndex": 20,
        "section": "Documents List",
        "subNumber": "21",
        "tabKey": "documents"
      },
      {
        "additionalInformation": "1",
        "caseNumber": "20-3-04134-7 SEA",
        "caseTypeKey": "family",
        "dateFiled": "09/22/2020",
        "documentName": "AFSR - Affidavit / Declaration / Certificate Of Service",
        "portalCaseId": "2812969",
        "rawCells": [
          "22",
          "09/22/2020",
          "AFSR - Affidavit / Declaration / Certificate Of Service",
          "1"
        ],
        "rawHeaders": [
          "Sub Number",
          "Date Filed",
          "Document Name",
          "Additional Information",
          "Filed By",
          "Page #",
          "Seal"
        ],
        "rawLine": "\t  22\t09/22/2020\tAFSR - Affidavit / Declaration / Certificate Of Service\t\t\t1\t",
        "rawTabId": "2812969:documents",
        "recordId": "2812969:documents:row:21",
        "rowIndex": 21,
        "section": "Documents List",
        "subNumber": "22",
        "tabKey": "documents"
      },
      {
        "additionalInformation": "Respondent - STEPHEN BENNETT",
        "caseNumber": "20-3-04134-7 SEA",
        "caseTypeKey": "family",
        "dateFiled": "09/28/2020",
        "documentName": "RSPMD - Response to Modification",
        "filedBy": "4",
        "portalCaseId": "2812969",
        "rawCells": [
          "23",
          "09/28/2020",
          "RSPMD - Response to Modification",
          "Respondent - STEPHEN BENNETT",
          "4"
        ],
        "rawHeaders": [
          "Sub Number",
          "Date Filed",
          "Document Name",
          "Additional Information",
          "Filed By",
          "Page #",
          "Seal"
        ],
        "rawLine": "\t  23\t09/28/2020\tRSPMD - Response to Modification\t\tRespondent - STEPHEN BENNETT\t4\t",
        "rawTabId": "2812969:documents",
        "recordId": "2812969:documents:row:22",
        "rowIndex": 22,
        "section": "Documents List",
        "subNumber": "23",
        "tabKey": "documents"
      },
      {
        "additionalInformation": "1",
        "caseNumber": "20-3-04134-7 SEA",
        "caseTypeKey": "family",
        "dateFiled": "09/28/2020",
        "documentName": "AFSR - Affidavit / Declaration / Certificate Of Service",
        "portalCaseId": "2812969",
        "rawCells": [
          "24",
          "09/28/2020",
          "AFSR - Affidavit / Declaration / Certificate Of Service",
          "1"
        ],
        "rawHeaders": [
          "Sub Number",
          "Date Filed",
          "Document Name",
          "Additional Information",
          "Filed By",
          "Page #",
          "Seal"
        ],
        "rawLine": "\t  24\t09/28/2020\tAFSR - Affidavit / Declaration / Certificate Of Service\t\t\t1\t",
        "rawTabId": "2812969:documents",
        "recordId": "2812969:documents:row:23",
        "rowIndex": 23,
        "section": "Documents List",
        "subNumber": "24",
        "tabKey": "documents"
      },
      {
        "additionalInformation": "DISMISSAL",
        "caseNumber": "20-3-04134-7 SEA",
        "caseTypeKey": "family",
        "dateFiled": "10/16/2020",
        "documentName": "NTMTDK - Note for Motion Docket",
        "filedBy": "Respondent - STEPHEN BENNETT",
        "pageCount": "2",
        "portalCaseId": "2812969",
        "rawCells": [
          "25",
          "10/16/2020",
          "NTMTDK - Note for Motion Docket",
          "DISMISSAL",
          "Respondent - STEPHEN BENNETT",
          "2"
        ],
        "rawHeaders": [
          "Sub Number",
          "Date Filed",
          "Document Name",
          "Additional Information",
          "Filed By",
          "Page #",
          "Seal"
        ],
        "rawLine": "\t  25\t10/16/2020\tNTMTDK - Note for Motion Docket\tDISMISSAL\tRespondent - STEPHEN BENNETT\t2\t",
        "rawTabId": "2812969:documents",
        "recordId": "2812969:documents:row:24",
        "rowIndex": 24,
        "section": "Documents List",
        "subNumber": "25",
        "tabKey": "documents"
      },
      {
        "additionalInformation": "Respondent - STEPHEN BENNETT",
        "caseNumber": "20-3-04134-7 SEA",
        "caseTypeKey": "family",
        "dateFiled": "10/16/2020",
        "documentName": "MTDSM - Motion to Dismiss",
        "filedBy": "20",
        "portalCaseId": "2812969",
        "rawCells": [
          "26",
          "10/16/2020",
          "MTDSM - Motion to Dismiss",
          "Respondent - STEPHEN BENNETT",
          "20"
        ],
        "rawHeaders": [
          "Sub Number",
          "Date Filed",
          "Document Name",
          "Additional Information",
          "Filed By",
          "Page #",
          "Seal"
        ],
        "rawLine": "\t  26\t10/16/2020\tMTDSM - Motion to Dismiss\t\tRespondent - STEPHEN BENNETT\t20\t",
        "rawTabId": "2812969:documents",
        "recordId": "2812969:documents:row:25",
        "rowIndex": 25,
        "section": "Documents List",
        "subNumber": "26",
        "tabKey": "documents"
      },
      {
        "additionalInformation": "OF STEPHEN ALLYN BENNETT",
        "caseNumber": "20-3-04134-7 SEA",
        "caseTypeKey": "family",
        "dateFiled": "10/16/2020",
        "documentName": "DCLR - Declaration",
        "filedBy": "4",
        "portalCaseId": "2812969",
        "rawCells": [
          "27",
          "10/16/2020",
          "DCLR - Declaration",
          "OF STEPHEN ALLYN BENNETT",
          "4"
        ],
        "rawHeaders": [
          "Sub Number",
          "Date Filed",
          "Document Name",
          "Additional Information",
          "Filed By",
          "Page #",
          "Seal"
        ],
        "rawLine": "\t  27\t10/16/2020\tDCLR - Declaration\tOF STEPHEN ALLYN BENNETT\t\t4\t",
        "rawTabId": "2812969:documents",
        "recordId": "2812969:documents:row:26",
        "rowIndex": 26,
        "section": "Documents List",
        "subNumber": "27",
        "tabKey": "documents"
      },
      {
        "additionalInformation": "OF THERESA R. LORELLA",
        "caseNumber": "20-3-04134-7 SEA",
        "caseTypeKey": "family",
        "dateFiled": "10/16/2020",
        "documentName": "DCLR - Declaration",
        "filedBy": "2",
        "portalCaseId": "2812969",
        "rawCells": [
          "28",
          "10/16/2020",
          "DCLR - Declaration",
          "OF THERESA R. LORELLA",
          "2"
        ],
        "rawHeaders": [
          "Sub Number",
          "Date Filed",
          "Document Name",
          "Additional Information",
          "Filed By",
          "Page #",
          "Seal"
        ],
        "rawLine": "\t  28\t10/16/2020\tDCLR - Declaration\tOF THERESA R. LORELLA\t\t2\t",
        "rawTabId": "2812969:documents",
        "recordId": "2812969:documents:row:27",
        "rowIndex": 27,
        "section": "Documents List",
        "subNumber": "28",
        "tabKey": "documents"
      },
      {
        "additionalInformation": "1",
        "caseNumber": "20-3-04134-7 SEA",
        "caseTypeKey": "family",
        "dateFiled": "10/16/2020",
        "documentName": "AFSR - Affidavit / Declaration / Certificate Of Service",
        "portalCaseId": "2812969",
        "rawCells": [
          "29",
          "10/16/2020",
          "AFSR - Affidavit / Declaration / Certificate Of Service",
          "1"
        ],
        "rawHeaders": [
          "Sub Number",
          "Date Filed",
          "Document Name",
          "Additional Information",
          "Filed By",
          "Page #",
          "Seal"
        ],
        "rawLine": "\t  29\t10/16/2020\tAFSR - Affidavit / Declaration / Certificate Of Service\t\t\t1\t",
        "rawTabId": "2812969:documents",
        "recordId": "2812969:documents:row:28",
        "rowIndex": 28,
        "section": "Documents List",
        "subNumber": "29",
        "tabKey": "documents"
      },
      {
        "additionalInformation": "DISMISSAL",
        "caseNumber": "20-3-04134-7 SEA",
        "caseTypeKey": "family",
        "dateFiled": "10/22/2020",
        "documentName": "NTMTDK - Note for Motion Docket",
        "filedBy": "Respondent - STEPHEN BENNETT",
        "pageCount": "2",
        "portalCaseId": "2812969",
        "rawCells": [
          "30",
          "10/22/2020",
          "NTMTDK - Note for Motion Docket",
          "DISMISSAL",
          "Respondent - STEPHEN BENNETT",
          "2"
        ],
        "rawHeaders": [
          "Sub Number",
          "Date Filed",
          "Document Name",
          "Additional Information",
          "Filed By",
          "Page #",
          "Seal"
        ],
        "rawLine": "\t  30\t10/22/2020\tNTMTDK - Note for Motion Docket\tDISMISSAL\tRespondent - STEPHEN BENNETT\t2\t",
        "rawTabId": "2812969:documents",
        "recordId": "2812969:documents:row:29",
        "rowIndex": 29,
        "section": "Documents List",
        "subNumber": "30",
        "tabKey": "documents"
      },
      {
        "additionalInformation": "1",
        "caseNumber": "20-3-04134-7 SEA",
        "caseTypeKey": "family",
        "dateFiled": "10/22/2020",
        "documentName": "AFSR - Affidavit / Declaration / Certificate Of Service",
        "portalCaseId": "2812969",
        "rawCells": [
          "31",
          "10/22/2020",
          "AFSR - Affidavit / Declaration / Certificate Of Service",
          "1"
        ],
        "rawHeaders": [
          "Sub Number",
          "Date Filed",
          "Document Name",
          "Additional Information",
          "Filed By",
          "Page #",
          "Seal"
        ],
        "rawLine": "\t  31\t10/22/2020\tAFSR - Affidavit / Declaration / Certificate Of Service\t\t\t1\t",
        "rawTabId": "2812969:documents",
        "recordId": "2812969:documents:row:30",
        "rowIndex": 30,
        "section": "Documents List",
        "subNumber": "31",
        "tabKey": "documents"
      },
      {
        "additionalInformation": "Petitioner - VANESSA GUYER",
        "caseNumber": "20-3-04134-7 SEA",
        "caseTypeKey": "family",
        "dateFiled": "11/09/2020",
        "documentName": "DCLR - Declaration",
        "filedBy": "22",
        "portalCaseId": "2812969",
        "rawCells": [
          "32",
          "11/09/2020",
          "DCLR - Declaration",
          "Petitioner - VANESSA GUYER",
          "22"
        ],
        "rawHeaders": [
          "Sub Number",
          "Date Filed",
          "Document Name",
          "Additional Information",
          "Filed By",
          "Page #",
          "Seal"
        ],
        "rawLine": "\t  32\t11/09/2020\tDCLR - Declaration\t\tPetitioner - VANESSA GUYER\t22\t",
        "rawTabId": "2812969:documents",
        "recordId": "2812969:documents:row:31",
        "rowIndex": 31,
        "section": "Documents List",
        "subNumber": "32",
        "tabKey": "documents"
      },
      {
        "additionalInformation": "1",
        "caseNumber": "20-3-04134-7 SEA",
        "caseTypeKey": "family",
        "dateFiled": "11/09/2020",
        "documentName": "AFSR - Affidavit / Declaration / Certificate Of Service",
        "portalCaseId": "2812969",
        "rawCells": [
          "34",
          "11/09/2020",
          "AFSR - Affidavit / Declaration / Certificate Of Service",
          "1"
        ],
        "rawHeaders": [
          "Sub Number",
          "Date Filed",
          "Document Name",
          "Additional Information",
          "Filed By",
          "Page #",
          "Seal"
        ],
        "rawLine": "\t  34\t11/09/2020\tAFSR - Affidavit / Declaration / Certificate Of Service\t\t\t1\t",
        "rawTabId": "2812969:documents",
        "recordId": "2812969:documents:row:32",
        "rowIndex": 32,
        "section": "Documents List",
        "subNumber": "34",
        "tabKey": "documents"
      },
      {
        "additionalInformation": "Petitioner - VANESSA GUYER",
        "caseNumber": "20-3-04134-7 SEA",
        "caseTypeKey": "family",
        "dateFiled": "11/09/2020",
        "documentName": "WPSL - Working Papers Submission List",
        "filedBy": "2",
        "portalCaseId": "2812969",
        "rawCells": [
          "35",
          "11/09/2020",
          "WPSL - Working Papers Submission List",
          "Petitioner - VANESSA GUYER",
          "2"
        ],
        "rawHeaders": [
          "Sub Number",
          "Date Filed",
          "Document Name",
          "Additional Information",
          "Filed By",
          "Page #",
          "Seal"
        ],
        "rawLine": "\t  35\t11/09/2020\tWPSL - Working Papers Submission List\t\tPetitioner - VANESSA GUYER\t2\t",
        "rawTabId": "2812969:documents",
        "recordId": "2812969:documents:row:33",
        "rowIndex": 33,
        "section": "Documents List",
        "subNumber": "35",
        "tabKey": "documents"
      },
      {
        "additionalInformation": "1",
        "caseNumber": "20-3-04134-7 SEA",
        "caseTypeKey": "family",
        "dateFiled": "11/09/2020",
        "documentName": "AFSR - Affidavit / Declaration / Certificate Of Service",
        "portalCaseId": "2812969",
        "rawCells": [
          "36",
          "11/09/2020",
          "AFSR - Affidavit / Declaration / Certificate Of Service",
          "1"
        ],
        "rawHeaders": [
          "Sub Number",
          "Date Filed",
          "Document Name",
          "Additional Information",
          "Filed By",
          "Page #",
          "Seal"
        ],
        "rawLine": "\t  36\t11/09/2020\tAFSR - Affidavit / Declaration / Certificate Of Service\t\t\t1\t",
        "rawTabId": "2812969:documents",
        "recordId": "2812969:documents:row:34",
        "rowIndex": 34,
        "section": "Documents List",
        "subNumber": "36",
        "tabKey": "documents"
      },
      {
        "additionalInformation": "TO MOTION TO DISMISS",
        "caseNumber": "20-3-04134-7 SEA",
        "caseTypeKey": "family",
        "dateFiled": "11/09/2020",
        "documentName": "RSP - Response",
        "filedBy": "Petitioner - VANESSA GUYER",
        "pageCount": "3",
        "portalCaseId": "2812969",
        "rawCells": [
          "37",
          "11/09/2020",
          "RSP - Response",
          "TO MOTION TO DISMISS",
          "Petitioner - VANESSA GUYER",
          "3"
        ],
        "rawHeaders": [
          "Sub Number",
          "Date Filed",
          "Document Name",
          "Additional Information",
          "Filed By",
          "Page #",
          "Seal"
        ],
        "rawLine": "\t  37\t11/09/2020\tRSP - Response\tTO MOTION TO DISMISS\tPetitioner - VANESSA GUYER\t3\t",
        "rawTabId": "2812969:documents",
        "recordId": "2812969:documents:row:35",
        "rowIndex": 35,
        "section": "Documents List",
        "subNumber": "37",
        "tabKey": "documents"
      },
      {
        "additionalInformation": "1",
        "caseNumber": "20-3-04134-7 SEA",
        "caseTypeKey": "family",
        "dateFiled": "11/09/2020",
        "documentName": "AFSR - Affidavit / Declaration / Certificate Of Service",
        "portalCaseId": "2812969",
        "rawCells": [
          "38",
          "11/09/2020",
          "AFSR - Affidavit / Declaration / Certificate Of Service",
          "1"
        ],
        "rawHeaders": [
          "Sub Number",
          "Date Filed",
          "Document Name",
          "Additional Information",
          "Filed By",
          "Page #",
          "Seal"
        ],
        "rawLine": "\t  38\t11/09/2020\tAFSR - Affidavit / Declaration / Certificate Of Service\t\t\t1\t",
        "rawTabId": "2812969:documents",
        "recordId": "2812969:documents:row:36",
        "rowIndex": 36,
        "section": "Documents List",
        "subNumber": "38",
        "tabKey": "documents"
      },
      {
        "additionalInformation": "REPLY IN SUPPORT OF HIS MOTION TO DISMISS AND FEES",
        "caseNumber": "20-3-04134-7 SEA",
        "caseTypeKey": "family",
        "dateFiled": "11/10/2020",
        "documentName": "DCLR - Declaration",
        "filedBy": "Respondent - STEPHEN BENNETT",
        "pageCount": "4",
        "portalCaseId": "2812969",
        "rawCells": [
          "39",
          "11/10/2020",
          "DCLR - Declaration",
          "REPLY IN SUPPORT OF HIS MOTION TO DISMISS AND FEES",
          "Respondent - STEPHEN BENNETT",
          "4"
        ],
        "rawHeaders": [
          "Sub Number",
          "Date Filed",
          "Document Name",
          "Additional Information",
          "Filed By",
          "Page #",
          "Seal"
        ],
        "rawLine": "\t  39\t11/10/2020\tDCLR - Declaration\tREPLY IN SUPPORT OF HIS MOTION TO DISMISS AND FEES\tRespondent - STEPHEN BENNETT\t4\t",
        "rawTabId": "2812969:documents",
        "recordId": "2812969:documents:row:37",
        "rowIndex": 37,
        "section": "Documents List",
        "subNumber": "39",
        "tabKey": "documents"
      },
      {
        "additionalInformation": "Respondent - STEPHEN BENNETT",
        "caseNumber": "20-3-04134-7 SEA",
        "caseTypeKey": "family",
        "dateFiled": "11/10/2020",
        "documentName": "WPSL - Working Papers Submission List",
        "filedBy": "2",
        "portalCaseId": "2812969",
        "rawCells": [
          "40",
          "11/10/2020",
          "WPSL - Working Papers Submission List",
          "Respondent - STEPHEN BENNETT",
          "2"
        ],
        "rawHeaders": [
          "Sub Number",
          "Date Filed",
          "Document Name",
          "Additional Information",
          "Filed By",
          "Page #",
          "Seal"
        ],
        "rawLine": "\t  40\t11/10/2020\tWPSL - Working Papers Submission List\t\tRespondent - STEPHEN BENNETT\t2\t",
        "rawTabId": "2812969:documents",
        "recordId": "2812969:documents:row:38",
        "rowIndex": 38,
        "section": "Documents List",
        "subNumber": "40",
        "tabKey": "documents"
      },
      {
        "additionalInformation": "1",
        "caseNumber": "20-3-04134-7 SEA",
        "caseTypeKey": "family",
        "dateFiled": "11/10/2020",
        "documentName": "AFSR - Affidavit / Declaration / Certificate Of Service",
        "portalCaseId": "2812969",
        "rawCells": [
          "41",
          "11/10/2020",
          "AFSR - Affidavit / Declaration / Certificate Of Service",
          "1"
        ],
        "rawHeaders": [
          "Sub Number",
          "Date Filed",
          "Document Name",
          "Additional Information",
          "Filed By",
          "Page #",
          "Seal"
        ],
        "rawLine": "\t  41\t11/10/2020\tAFSR - Affidavit / Declaration / Certificate Of Service\t\t\t1\t",
        "rawTabId": "2812969:documents",
        "recordId": "2812969:documents:row:39",
        "rowIndex": 39,
        "section": "Documents List",
        "subNumber": "41",
        "tabKey": "documents"
      },
      {
        "additionalInformation": "2",
        "caseNumber": "20-3-04134-7 SEA",
        "caseTypeKey": "family",
        "dateFiled": "11/17/2020",
        "documentName": "ORDSM - Order of Dismissal",
        "portalCaseId": "2812969",
        "rawCells": [
          "42",
          "11/17/2020",
          "ORDSM - Order of Dismissal",
          "2"
        ],
        "rawHeaders": [
          "Sub Number",
          "Date Filed",
          "Document Name",
          "Additional Information",
          "Filed By",
          "Page #",
          "Seal"
        ],
        "rawLine": "\t  42\t11/17/2020\tORDSM - Order of Dismissal\t\t\t2\t",
        "rawTabId": "2812969:documents",
        "recordId": "2812969:documents:row:40",
        "rowIndex": 40,
        "section": "Documents List",
        "subNumber": "42",
        "tabKey": "documents"
      },
      {
        "additionalInformation": "Petitioner - VANESSA GUYER",
        "caseNumber": "20-3-04134-7 SEA",
        "caseTypeKey": "family",
        "dateFiled": "01/13/2021",
        "documentName": "NTIWD - Notice of Intent to Withdraw",
        "filedBy": "2",
        "portalCaseId": "2812969",
        "rawCells": [
          "43",
          "01/13/2021",
          "NTIWD - Notice of Intent to Withdraw",
          "Petitioner - VANESSA GUYER",
          "2"
        ],
        "rawHeaders": [
          "Sub Number",
          "Date Filed",
          "Document Name",
          "Additional Information",
          "Filed By",
          "Page #",
          "Seal"
        ],
        "rawLine": "\t  43\t01/13/2021\tNTIWD - Notice of Intent to Withdraw\t\tPetitioner - VANESSA GUYER\t2\t",
        "rawTabId": "2812969:documents",
        "recordId": "2812969:documents:row:41",
        "rowIndex": 41,
        "section": "Documents List",
        "subNumber": "43",
        "tabKey": "documents"
      },
      {
        "additionalInformation": "Respondent - STEPHEN BENNETT",
        "caseNumber": "20-3-04134-7 SEA",
        "caseTypeKey": "family",
        "dateFiled": "03/30/2021",
        "documentName": "NTIWD - Notice of Intent to Withdraw",
        "filedBy": "3",
        "portalCaseId": "2812969",
        "rawCells": [
          "44",
          "03/30/2021",
          "NTIWD - Notice of Intent to Withdraw",
          "Respondent - STEPHEN BENNETT",
          "3"
        ],
        "rawHeaders": [
          "Sub Number",
          "Date Filed",
          "Document Name",
          "Additional Information",
          "Filed By",
          "Page #",
          "Seal"
        ],
        "rawLine": "\t  44\t03/30/2021\tNTIWD - Notice of Intent to Withdraw\t\tRespondent - STEPHEN BENNETT\t3\t",
        "rawTabId": "2812969:documents",
        "recordId": "2812969:documents:row:42",
        "rowIndex": 42,
        "section": "Documents List",
        "subNumber": "44",
        "tabKey": "documents"
      },
      {
        "additionalInformation": "Clerk",
        "caseNumber": "20-3-04134-7 SEA",
        "caseTypeKey": "family",
        "dateFiled": "04/07/2021",
        "documentName": "FAULTY - Faulty Document Notice",
        "filedBy": "1",
        "portalCaseId": "2812969",
        "rawCells": [
          "45",
          "04/07/2021",
          "FAULTY - Faulty Document Notice",
          "Clerk",
          "1"
        ],
        "rawHeaders": [
          "Sub Number",
          "Date Filed",
          "Document Name",
          "Additional Information",
          "Filed By",
          "Page #",
          "Seal"
        ],
        "rawLine": "\t  45\t04/07/2021\tFAULTY - Faulty Document Notice\t\tClerk\t1\t",
        "rawTabId": "2812969:documents",
        "recordId": "2812969:documents:row:43",
        "rowIndex": 43,
        "section": "Documents List",
        "subNumber": "45",
        "tabKey": "documents"
      }
    ],
    "judgment_rows": [],
    "next_hearing": null,
    "portal_case_id": "2812969",
    "portal_node_id": "420",
    "raw_tab_summaries": [
      {
        "blockedDetailPage": false,
        "caseNumber": "20-3-04134-7 SEA",
        "caseNumberPresent": true,
        "caseTypeKey": "family",
        "folder": "FV-Public-Case-Documents-Portal",
        "headings": [
          "Main navigation",
          "User Menu",
          "Case Data",
          "Documents",
          "Documents List"
        ],
        "label": "Document List",
        "pageTextLength": 4153,
        "pageTextSha256": "7d3897d8ba79548c50f58d36855dc46c763abb299a24f4622ff22fb4badbb41b",
        "portalCaseId": "2812969",
        "rawDetailRecordRef": "case-details.ndjson:93",
        "rawTabId": "2812969:documents",
        "tabKey": "documents",
        "tableCount": 5,
        "title": "Case Data | King County Superior Court Clerk's Office",
        "url": "https://dja-prd-ecexap1.kingcounty.gov/node/420?Id=2812969&folder=FV-Public-Case-Documents-Portal"
      },
      {
        "blockedDetailPage": false,
        "caseNumber": "20-3-04134-7 SEA",
        "caseNumberPresent": true,
        "caseTypeKey": "family",
        "folder": "FV-Public-Case-Events-Portal",
        "headings": [
          "Main navigation",
          "User Menu",
          "Case Data",
          "Events",
          "Hearings",
          "Case Schedule - SubCase",
          "Time Standards"
        ],
        "label": "Events",
        "pageTextLength": 1578,
        "pageTextSha256": "3abd56fc7612f37bec9e4521e128090b1704445c19fa4169392b95c7ae5d8f3f",
        "portalCaseId": "2812969",
        "rawDetailRecordRef": "case-details.ndjson:93",
        "rawTabId": "2812969:events_docket",
        "tabKey": "events_docket",
        "tableCount": 6,
        "title": "Case Data | King County Superior Court Clerk's Office",
        "url": "https://dja-prd-ecexap1.kingcounty.gov/node/420?Id=2812969&folder=FV-Public-Case-Events-Portal"
      },
      {
        "blockedDetailPage": false,
        "caseNumber": "20-3-04134-7 SEA",
        "caseNumberPresent": true,
        "caseTypeKey": "family",
        "folder": "FV-Court-Judgments-Portal-New",
        "headings": [
          "Main navigation",
          "User Menu",
          "Case Data",
          "Judgments",
          "Judgments"
        ],
        "label": "Judgments",
        "pageTextLength": 870,
        "pageTextSha256": "4daf69a81dff3a2da9a249f762ad2a37a5cb7ca573ab1860152fe3a5449073d7",
        "portalCaseId": "2812969",
        "rawDetailRecordRef": "case-details.ndjson:93",
        "rawTabId": "2812969:judgments",
        "tabKey": "judgments",
        "tableCount": 5,
        "title": "Case Data | King County Superior Court Clerk's Office",
        "url": "https://dja-prd-ecexap1.kingcounty.gov/node/420?Id=2812969&folder=FV-Court-Judgments-Portal-New"
      },
      {
        "blockedDetailPage": false,
        "caseNumber": "20-3-04134-7 SEA",
        "caseNumberPresent": true,
        "caseTypeKey": "family",
        "folder": "FV-Public-Case-Participants-Portal",
        "headings": [
          "Main navigation",
          "User Menu",
          "Case Data",
          "Participants",
          "Participants"
        ],
        "label": "Participants",
        "pageTextLength": 1301,
        "pageTextSha256": "4602e867a2ad62d5f9513cee36248dcf7120ec16acae2804c8d6f5d9da471aad",
        "portalCaseId": "2812969",
        "rawDetailRecordRef": "case-details.ndjson:93",
        "rawTabId": "2812969:participants",
        "tabKey": "participants",
        "tableCount": 4,
        "title": "Case Data | King County Superior Court Clerk's Office",
        "url": "https://dja-prd-ecexap1.kingcounty.gov/node/420?Id=2812969&folder=FV-Public-Case-Participants-Portal"
      },
      {
        "blockedDetailPage": false,
        "caseNumber": "20-3-04134-7 SEA",
        "caseNumberPresent": true,
        "caseTypeKey": "family",
        "folder": "FV-Public-Case-Summary-Portal",
        "headings": [
          "Main navigation",
          "User Menu",
          "Case Data",
          "Case Summary",
          "Summary"
        ],
        "label": "Summary",
        "pageTextLength": 913,
        "pageTextSha256": "c8068483aa296bca44f7737d705cae59b4ee008113d458eb38777b8f65f42195",
        "portalCaseId": "2812969",
        "rawDetailRecordRef": "case-details.ndjson:93",
        "rawTabId": "2812969:summary",
        "tabKey": "summary",
        "tableCount": 4,
        "title": "Case Data | King County Superior Court Clerk's Office",
        "url": "https://dja-prd-ecexap1.kingcounty.gov/node/420?Id=2812969&folder=FV-Public-Case-Summary-Portal"
      }
    ],
    "source_status": "Completed 11/17/2020"
  },
  "parties": [
    {
      "attorneys": [
        "Petition - filed on 09/02/2020 Disposed as DSM - Dismissal Without Trial on 11/17/2020"
      ],
      "case_number": "203041347SEA",
      "name": "Petition - filed on 09/02/2020 Disposed as DSM - Dismissal Without Trial on 11/17/2020",
      "party_address": null,
      "party_id": "203041347SEA:party:1",
      "party_seq": 1,
      "party_type": "- filed on 08/25/2020 Disposed as TRJG - Transfer Of Judgment on 08/25/2020",
      "raw": {
        "caseNumber": "20-3-04134-7 SEA",
        "caseTypeKey": "family",
        "name": "Petition - filed on 09/02/2020 Disposed as DSM - Dismissal Without Trial on 11/17/2020",
        "portalCaseId": "2812969",
        "rawCells": [
          "- filed on 08/25/2020 Disposed as TRJG - Transfer Of Judgment on 08/25/2020",
          "Petition - filed on 09/02/2020 Disposed as DSM - Dismissal Without Trial on 11/17/2020",
          "Petition - filed on 09/02/2020 Disposed as DSM - Dismissal Without Trial on 11/17/2020"
        ],
        "rawHeaders": [
          "Type",
          "Name",
          "Represented By"
        ],
        "rawLine": "- filed on 08/25/2020 Disposed as TRJG - Transfer Of Judgment on 08/25/2020\tPetition - filed on 09/02/2020 Disposed as DSM - Dismissal Without Trial on 11/17/2020\tPetition - filed on 09/02/2020 Disposed as DSM - Dismissal Without Trial on 11/17/2020",
        "rawTabId": "2812969:participants",
        "recordId": "2812969:participants:row:1",
        "representedBy": "Petition - filed on 09/02/2020 Disposed as DSM - Dismissal Without Trial on 11/17/2020",
        "rowIndex": 1,
        "section": "Out of State Support Registration /Foreign Judgment (3) - Completed/Re-Completed",
        "tabKey": "participants",
        "type": "- filed on 08/25/2020 Disposed as TRJG - Transfer Of Judgment on 08/25/2020"
      },
      "source": "kcsc.participants"
    }
  ],
  "payments": [],
  "raw": {
    "case": {
      "caseName": "SANTAMARIA AKA VS BENNETT",
      "caseNumber": "20-3-04134-7 SEA",
      "caseTypeKey": "family",
      "caseTypeText": "3 - Domestic",
      "chargeOrCause": "Out of State Support Registration /Foreign Judgment (3)",
      "dateText": "08/25/2020",
      "detailCapturedAt": "2026-07-15T05:10:42.768Z",
      "detailError": {},
      "detailErrorCapturedAt": "",
      "detailHref": "https://dja-prd-ecexap1.kingcounty.gov/node/411?q=node/420/2812969",
      "detailStatus": "captured",
      "detailUnavailableReason": "",
      "discoveredTabCount": 5,
      "filingDate": "08/25/2020",
      "nextHearing": "",
      "pageNum": 1,
      "portalCaseId": "2812969",
      "portalNodeId": "420",
      "rawDetailRecordRef": "case-details.ndjson:93",
      "rawSearchRowRef": "search-rows.ndjson:93",
      "searchKey": "family_08_25_2020",
      "status": "Completed 11/17/2020"
    }
  },
  "source": "kcsc_portal",
  "source_url": "https://dja-prd-ecexap1.kingcounty.gov/node/411?q=node/420/2812969",
  "status": "Completed 11/17/2020",
  "updated_at": "2026-07-15T05:10:42.768Z"
}
